django_admin_env_notice/__init__.py
django_admin_env_notice/apps.py
django_admin_env_notice/context_processors.py
django_admin_env_notice/views.py
django_admin_env_notice/templates/admin/base_site.html
django_admin_env_notice-1.0.1.dist-info/AUTHORS.rst
django_admin_env_notice-1.0.1.dist-info/LICENSE
django_admin_env_notice-1.0.1.dist-info/METADATA
django_admin_env_notice-1.0.1.dist-info/WHEEL
django_admin_env_notice-1.0.1.dist-info/top_level.txt
django_admin_env_notice-1.0.1.dist-info/RECORD
